{
  "employee": [
    {
      "id": 1,
      "name": "json",
      "email": "siva@gamil.com",
      "phone": "3445662778"
    },
    {
      "id": 6,
      "name": "vasanth",
      "email": "vasanth@gmail.com",
      "phone": "1",
      "Active": "true"
    },
    {
      "id": 7,
      "name": "siva",
      "email": "siva@gmail.com",
      "phone": "23456",
      "Active": "true"
    },
    {
      "id": 8,
      "name": "Mathan Prasanth",
      "email": "mathan@gmail.com",
      "phone": "3445566",
      "Active": false
    },
    {
      "id": 9,
      "name": "yy",
      "email": "hjj",
      "phone": "677",
      "Active": "true"
    },
    {
      "id": 10,
      "name": "ttyy",
      "email": "tty",
      "phone": "4566",
      "Active": "true"
    }
  ]
}